{"eventState": {}, "tournament": {"name": "Premier League", "slug": "premier-league", "category": {"name": "England", "slug": "england", "sport": {"name": "Football", "slug": "football", "id": 1}, "country": {"alpha2": "EN", "alpha3": "ENG", "name": "England", "slug": "england"}, "id": 1, "flag": "england", "alpha2": "EN", "fieldTranslations": {"nameTranslation": {"ar": "\u0625\u0646\u062c\u0644\u062a\u0631\u0627", "hi": "\u0907\u0902\u0917\u094d\u0932\u0948\u0902\u0921", "bn": "\u0987\u0982\u09b2\u09cd\u09af\u09be\u09a8\u09cd\u09a1", "ru": "\u0410\u043d\u0433\u043b\u0438\u044f"}, "shortNameTranslation": {}}}, "uniqueTournament": {"name": "Premier League", "slug": "premier-league", "primaryColorHex": "#3c1c5a", "secondaryColorHex": "#f80158", "category": {"name": "England", "slug": "england", "sport": {"name": "Football", "slug": "football", "id": 1}, "country": {"alpha2": "EN", "alpha3": "ENG", "name": "England", "slug": "england"}, "id": 1, "flag": "england", "alpha2": "EN", "fieldTranslations": {"nameTranslation": {"ar": "\u0625\u0646\u062c\u0644\u062a\u0631\u0627", "hi": "\u0907\u0902\u0917\u094d\u0932\u0948\u0902\u0921", "bn": "\u0987\u0982\u09b2\u09cd\u09af\u09be\u09a8\u09cd\u09a1", "ru": "\u0410\u043d\u0433\u043b\u0438\u044f"}, "shortNameTranslation": {}}}, "userCount": 1163256, "hasPerformanceGraphFeature": true, "country": {}, "id": 17, "hasEventPlayerStatistics": true, "displayInverseHomeAwayTeams": false, "fieldTranslations": {"nameTranslation": {"ar": "\u0627\u0644\u062f\u0648\u0631\u064a \u0627\u0644\u0625\u0646\u062c\u0644\u064a\u0632\u064a \u0627\u0644\u0645\u0645\u062a\u0627\u0632", "hi": "\u092a\u094d\u0930\u093f\u092e\u093f\u092f\u0930 \u0932\u0940\u0917", "bn": "\u09aa\u09cd\u09b0\u09bf\u09ae\u09bf\u09df\u09be\u09b0 \u09b2\u09c0\u0997"}, "shortNameTranslation": {}}}, "priority": 701, "isGroup": false, "isLive": false, "id": 1, "fieldTranslations": {"nameTranslation": {"hi": "\u092a\u094d\u0930\u093f\u092e\u093f\u092f\u0930 \u0932\u0940\u0917", "ar": "\u0627\u0644\u062f\u0648\u0631\u064a \u0627\u0644\u0625\u0646\u062c\u0644\u064a\u0632\u064a \u0627\u0644\u0645\u0645\u062a\u0627\u0632", "bn": "\u09aa\u09cd\u09b0\u09bf\u09ae\u09bf\u09af\u09bc\u09be\u09b0 \u09b2\u09c0\u0997"}, "shortNameTranslation": {}}}, "season": {"name": "Premier League 21/22", "year": "21/22", "editor": false, "id": 37036}, "roundInfo": {"round": 18}, "customId": "rO", "status": {"code": 100, "description": "Ended", "type": "finished"}, "winnerCode": 2, "homeTeam": {"name": "Newcastle United", "slug": "newcastle-united", "shortName": "Newcastle", "gender": "M", "sport": {"name": "Football", "slug": "football", "id": 1}, "userCount": 876239, "nameCode": "NEW", "disabled": false, "national": false, "type": 0, "country": {"alpha2": "EN", "alpha3": "ENG", "name": "England", "slug": "england"}, "id": 39, "subTeams": [], "teamColors": {"primary": "#000000", "secondary": "#ffffff", "text": "#ffffff"}, "fieldTranslations": {"nameTranslation": {"ar": "\u0646\u064a\u0648\u0643\u0627\u0633\u0644 \u064a\u0648\u0646\u0627\u064a\u062a\u062f", "hi": "\u0928\u094d\u092f\u0942 \u0915\u093e\u0938\u094d\u0938\u0947\u0932 \u092f\u0942\u0928\u093e\u0907\u091f\u0947\u0921 \u090d\u095e\u0938\u0940", "ru": "\u041d\u044c\u044e\u043a\u0430\u0441\u043b \u042e\u043d\u0430\u0439\u0442\u0435\u0434"}, "shortNameTranslation": {"ar": "\u0646\u064a\u0648\u0643\u0627\u0633\u0644", "bn": "\u09a8\u09bf\u0989\u0995\u09cd\u09af\u09be\u09b8\u09b2", "hi": "\u0928\u094d\u092f\u0942\u0915\u0948\u0938\u0932"}}}, "awayTeam": {"name": "Manchester City", "slug": "manchester-city", "shortName": "Man City", "gender": "M", "sport": {"name": "Football", "slug": "football", "id": 1}, "userCount": 3737604, "nameCode": "MCI", "disabled": false, "national": false, "type": 0, "country": {"alpha2": "EN", "alpha3": "ENG", "name": "England", "slug": "england"}, "id": 17, "subTeams": [], "teamColors": {"primary": "#66ccff", "secondary": "#ffffff", "text": "#ffffff"}, "fieldTranslations": {"nameTranslation": {"ar": "\u0645\u0627\u0646\u0634\u0633\u062a\u0631 \u0633\u064a\u062a\u064a", "hi": "\u092e\u0947\u0928\u091a\u0947\u0938\u094d\u091f\u0930 \u0938\u093f\u091f\u0940 \u090d\u095e\u0938\u0940", "ru": "\u041c\u0430\u043d\u0447\u0435\u0441\u0442\u0435\u0440 \u0421\u0438\u0442\u0438"}, "shortNameTranslation": {"ar": "\u0645\u0627\u0646 \u0633\u064a\u062a\u064a", "bn": "\u09ae\u09cd\u09af\u09be\u09a8 \u09b8\u09bf\u099f\u09bf", "hi": "\u092e\u0948\u0928 \u0938\u093f\u091f\u0940"}}}, "homeScore": {"current": 0, "display": 0, "period1": 0, "normaltime": 0}, "awayScore": {"current": 4, "display": 4, "period1": 2, "normaltime": 4}, "coverage": 1, "time": {"injuryTime1": 1, "injuryTime2": 2, "currentPeriodStartTimestamp": 1639928933}, "changes": {"changes": ["status.code", "status.description", "status.type", "homeScore.normaltime", "awayScore.normaltime", "time.currentPeriodStart"], "changeTimestamp": 1639928935}, "hasGlobalHighlights": false, "hasEventPlayerStatistics": true, "hasEventPlayerHeatMap": true, "detailId": 1, "crowdsourcingDataDisplayEnabled": false, "id": 9576096, "slug": "newcastle-united-manchester-city", "startTimestamp": 1639922400, "finalResultOnly": false, "feedLocked": false, "isEditor": false, "_stats": {"home_ballPossession": 28, "away_ballPossession": 72, "home_bigChanceCreated": 0, "away_bigChanceCreated": 5, "home_totalShotsOnGoal": 5, "away_totalShotsOnGoal": 18, "home_goalkeeperSaves": 3, "away_goalkeeperSaves": 1, "home_cornerKicks": 3, "away_cornerKicks": 6, "home_fouls": 9, "away_fouls": 6, "home_passes": 265, "away_passes": 709, "home_totalTackle": 13, "away_totalTackle": 21, "home_freeKicks": 6, "away_freeKicks": 8, "home_yellowCards": 1, "away_yellowCards": 2, "home_shotsOnGoal": 1, "away_shotsOnGoal": 7, "home_hitWoodwork": 0, "away_hitWoodwork": 0, "home_shotsOffGoal": 4, "away_shotsOffGoal": 8, "home_blockedScoringAttempt": 0, "away_blockedScoringAttempt": 3, "home_totalShotsInsideBox": 2, "away_totalShotsInsideBox": 16, "home_totalShotsOutsideBox": 3, "away_totalShotsOutsideBox": 2, "home_bigChanceScored": 0, "away_bigChanceScored": 3, "home_bigChanceMissed": 0, "away_bigChanceMissed": 2, "home_accurateThroughBall": 1, "away_accurateThroughBall": 1, "home_fouledFinalThird": 3, "away_fouledFinalThird": 1, "home_offsides": 4, "away_offsides": 2, "home_accuratePasses": 215, "away_accuratePasses": 646, "home_throwIns": 14, "away_throwIns": 15, "home_finalThirdEntries": 38, "away_finalThirdEntries": 62, "home_accurateLongBalls": 23, "away_accurateLongBalls": 26, "home_accurateCross": 2, "away_accurateCross": 5, "home_duelWonPercent": 45, "away_duelWonPercent": 55, "home_dispossessed": 12, "away_dispossessed": 6, "home_groundDuelsPercentage": 28, "away_groundDuelsPercentage": 40, "home_aerialDuelsPercentage": 12, "away_aerialDuelsPercentage": 8, "home_dribblesPercentage": 9, "away_dribblesPercentage": 11, "home_wonTacklePercent": 7, "away_wonTacklePercent": 10, "home_interceptionWon": 11, "away_interceptionWon": 5, "home_totalClearance": 16, "away_totalClearance": 9, "home_goalKicks": 8, "away_goalKicks": 7}}