{"eventState": {}, "tournament": {"name": "UEFA Champions League, Group C", "slug": "uefa-champions-league-group-c", "category": {"name": "Europe", "slug": "europe", "sport": {"name": "Football", "slug": "football", "id": 1}, "country": {}, "id": 1465, "flag": "europe", "fieldTranslations": {"nameTranslation": {"ar": "\u0623\u0648\u0631\u0648\u0628\u0627", "hi": "\u092f\u0942\u0930\u094b\u092a", "bn": "\u0987\u0989\u09b0\u09cb\u09aa", "ru": "\u0415\u0432\u0440\u043e\u043f\u0430"}, "shortNameTranslation": {}}}, "uniqueTournament": {"name": "UEFA Champions League", "slug": "uefa-champions-league", "primaryColorHex": "#062b5c", "secondaryColorHex": "#086aab", "category": {"name": "Europe", "slug": "europe", "sport": {"name": "Football", "slug": "football", "id": 1}, "country": {}, "id": 1465, "flag": "europe", "fieldTranslations": {"nameTranslation": {"ar": "\u0623\u0648\u0631\u0648\u0628\u0627", "hi": "\u092f\u0942\u0930\u094b\u092a", "bn": "\u0987\u0989\u09b0\u09cb\u09aa", "ru": "\u0415\u0432\u0440\u043e\u043f\u0430"}, "shortNameTranslation": {}}}, "userCount": 1194230, "hasPerformanceGraphFeature": false, "country": {}, "id": 7, "hasEventPlayerStatistics": true, "displayInverseHomeAwayTeams": false, "fieldTranslations": {"nameTranslation": {"bn": "\u0989\u09af\u09bc\u09c7\u09ab\u09be \u099a\u09cd\u09af\u09be\u09ae\u09cd\u09aa\u09bf\u09af\u09bc\u09a8\u09cd\u09b8 \u09b2\u09c0\u0997", "ar": "\u062f\u0648\u0631\u064a \u0623\u0628\u0637\u0627\u0644 \u0623\u0648\u0631\u0648\u0628\u0627", "hi": "\u092f\u0942\u0908\u090f\u092b\u090f \u091a\u0948\u0902\u092a\u093f\u092f\u0902\u0938 \u0932\u0940\u0917", "hr": "UEFA Liga prvaka"}, "shortNameTranslation": {}}}, "priority": 710, "isGroup": true, "groupName": "Group C", "groupSign": "C", "isLive": false, "id": 1464, "fieldTranslations": {"nameTranslation": {"hi": "\u092f\u0942\u0908\u090f\u092b\u090f \u091a\u0948\u0902\u092a\u093f\u092f\u0902\u0938 \u0932\u0940\u0917, \u0917\u094d\u0930\u0941\u092a \u0938\u0940", "ar": "\u062f\u0648\u0631\u064a \u0623\u0628\u0637\u0627\u0644 \u0623\u0648\u0631\u0648\u0628\u0627\u060c \u0627\u0644\u0645\u062c\u0645\u0648\u0639\u0629 \u0627\u0644\u062b\u0627\u0644\u062b\u0629", "bn": "\u0989\u09af\u09bc\u09c7\u09ab\u09be \u099a\u09cd\u09af\u09be\u09ae\u09cd\u09aa\u09bf\u09af\u09bc\u09a8\u09cd\u09b8 \u09b2\u09c0\u0997, \u0997\u09cd\u09b0\u09c1\u09aa \u09b8\u09bf"}, "shortNameTranslation": {}}}, "season": {"name": "UEFA Champions League 23/24", "year": "23/24", "editor": false, "seasonCoverageInfo": {}, "id": 52162}, "roundInfo": {"round": 2}, "customId": "oebsEgb", "status": {"code": 100, "description": "Ended", "type": "finished"}, "winnerCode": 2, "homeTeam": {"name": "Napoli", "slug": "napoli", "shortName": "Napoli", "gender": "M", "sport": {"name": "Football", "slug": "football", "id": 1}, "userCount": 1086749, "nameCode": "NAP", "disabled": false, "national": false, "type": 0, "country": {"alpha2": "IT", "alpha3": "ITA", "name": "Italy", "slug": "italy"}, "id": 2714, "subTeams": [], "teamColors": {"primary": "#008cea", "secondary": "#ffffff", "text": "#ffffff"}, "fieldTranslations": {"nameTranslation": {"ar": "\u0646\u0627\u0628\u0648\u0644\u064a", "bn": "\u09a8\u09be\u09aa\u09cb\u09b2\u09bf", "hi": "\u0928\u0947\u092a\u094b\u0932\u0940", "ru": "\u041d\u0430\u043f\u043e\u043b\u0438"}, "shortNameTranslation": {}}}, "awayTeam": {"name": "Real Madrid", "slug": "real-madrid", "shortName": "Real Madrid", "gender": "M", "sport": {"name": "Football", "slug": "football", "id": 1}, "userCount": 6823844, "nameCode": "RMA", "disabled": false, "national": false, "type": 0, "country": {"alpha2": "ES", "alpha3": "ESP", "name": "Spain", "slug": "spain"}, "id": 2829, "subTeams": [], "teamColors": {"primary": "#ffffff", "secondary": "#004996", "text": "#004996"}, "fieldTranslations": {"nameTranslation": {"ar": "\u0631\u064a\u0627\u0644 \u0645\u062f\u0631\u064a\u062f", "bn": "\u09b0\u09bf\u09af\u09bc\u09be\u09b2 \u09ae\u09be\u09a6\u09cd\u09b0\u09bf\u09a6", "hi": "\u0930\u093f\u092f\u0932 \u092e\u0948\u0921\u094d\u0930\u093f\u0921", "ru": "\u0420\u0435\u0430\u043b \u041c\u0430\u0434\u0440\u0438\u0434"}, "shortNameTranslation": {}}}, "homeScore": {"current": 2, "display": 2, "period1": 1, "period2": 1, "normaltime": 2}, "awayScore": {"current": 3, "display": 3, "period1": 2, "period2": 1, "normaltime": 3}, "time": {"injuryTime1": 1, "injuryTime2": 5, "currentPeriodStartTimestamp": 1696363471}, "changes": {"changes": ["time.currentPeriodStart"], "changeTimestamp": 1702408510}, "hasGlobalHighlights": false, "hasXg": true, "hasEventPlayerStatistics": true, "hasEventPlayerHeatMap": true, "detailId": 1, "crowdsourcingDataDisplayEnabled": false, "id": 11605847, "slug": "real-madrid-napoli", "startTimestamp": 1696359600, "finalResultOnly": false, "feedLocked": true, "isEditor": false, "_stats": {"home_ballPossession": 50, "away_ballPossession": 50, "home_expectedGoals": 1.98, "away_expectedGoals": 1.48, "home_bigChanceCreated": 2, "away_bigChanceCreated": 3, "home_totalShotsOnGoal": 18, "away_totalShotsOnGoal": 18, "home_goalkeeperSaves": 3, "away_goalkeeperSaves": 5, "home_cornerKicks": 9, "away_cornerKicks": 9, "home_fouls": 9, "away_fouls": 12, "home_passes": 506, "away_passes": 515, "home_totalTackle": 16, "away_totalTackle": 23, "home_freeKicks": 10, "away_freeKicks": 8, "home_yellowCards": 1, "away_yellowCards": 3, "home_shotsOnGoal": 7, "away_shotsOnGoal": 5, "home_hitWoodwork": 1, "away_hitWoodwork": 1, "home_shotsOffGoal": 4, "away_shotsOffGoal": 4, "home_blockedScoringAttempt": 7, "away_blockedScoringAttempt": 9, "home_totalShotsInsideBox": 10, "away_totalShotsInsideBox": 13, "home_totalShotsOutsideBox": 8, "away_totalShotsOutsideBox": 5, "home_bigChanceScored": 1, "away_bigChanceScored": 1, "home_bigChanceMissed": 1, "away_bigChanceMissed": 2, "home_accurateThroughBall": 2, "away_accurateThroughBall": 0, "home_fouledFinalThird": 2, "away_fouledFinalThird": 2, "home_offsides": 0, "away_offsides": 1, "home_accuratePasses": 457, "away_accuratePasses": 460, "home_throwIns": 12, "away_throwIns": 12, "home_finalThirdEntries": 42, "away_finalThirdEntries": 57, "home_accurateLongBalls": 29, "away_accurateLongBalls": 15, "home_accurateCross": 2, "away_accurateCross": 3, "home_duelWonPercent": 41, "away_duelWonPercent": 59, "home_dispossessed": 16, "away_dispossessed": 8, "home_groundDuelsPercentage": 32, "away_groundDuelsPercentage": 40, "home_aerialDuelsPercentage": 11, "away_aerialDuelsPercentage": 22, "home_dribblesPercentage": 6, "away_dribblesPercentage": 11, "home_wonTacklePercent": 11, "away_wonTacklePercent": 13, "home_interceptionWon": 8, "away_interceptionWon": 6, "home_ballRecovery": 41, "away_ballRecovery": 40, "home_totalClearance": 12, "away_totalClearance": 25, "home_goalsPrevented": -1.0234, "away_goalsPrevented": -0.1908, "home_goalKicks": 7, "away_goalKicks": 9}}