{"eventState": {}, "tournament": {"name": "Bundesliga", "slug": "bundesliga", "category": {"name": "Germany", "slug": "germany", "sport": {"name": "Football", "slug": "football", "id": 1}, "country": {"alpha2": "DE", "alpha3": "DEU", "name": "Germany", "slug": "germany"}, "id": 30, "flag": "germany", "alpha2": "DE", "fieldTranslations": {"nameTranslation": {"ar": "\u0623\u0644\u0645\u0627\u0646\u064a\u0627", "bn": "\u099c\u09be\u09b0\u09cd\u09ae\u09be\u09a8\u09bf", "hi": "\u091c\u0930\u094d\u092e\u0928\u0940", "ru": "\u0413\u0435\u0440\u043c\u0430\u043d\u0438\u044f"}, "shortNameTranslation": {}}}, "uniqueTournament": {"name": "Bundesliga", "slug": "bundesliga", "primaryColorHex": "#e2080e", "secondaryColorHex": "#8e0902", "category": {"name": "Germany", "slug": "germany", "sport": {"name": "Football", "slug": "football", "id": 1}, "country": {"alpha2": "DE", "alpha3": "DEU", "name": "Germany", "slug": "germany"}, "id": 30, "flag": "germany", "alpha2": "DE", "fieldTranslations": {"nameTranslation": {"ar": "\u0623\u0644\u0645\u0627\u0646\u064a\u0627", "bn": "\u099c\u09be\u09b0\u09cd\u09ae\u09be\u09a8\u09bf", "hi": "\u091c\u0930\u094d\u092e\u0928\u0940", "ru": "\u0413\u0435\u0440\u043c\u0430\u043d\u0438\u044f"}, "shortNameTranslation": {}}}, "userCount": 509847, "hasPerformanceGraphFeature": true, "country": {}, "id": 35, "hasEventPlayerStatistics": true, "displayInverseHomeAwayTeams": false, "fieldTranslations": {"nameTranslation": {"bn": "\u09ac\u09c1\u09a8\u09cd\u09a6\u09c7\u09b8\u09b2\u09c0\u0997\u09be", "ar": "\u0627\u0644\u062f\u0648\u0631\u064a \u0627\u0644\u0623\u0644\u0645\u0627\u0646\u064a", "hi": "\u092c\u0941\u0902\u0921\u0947\u0938\u0932\u0940\u0917\u093e"}, "shortNameTranslation": {}}}, "priority": 697, "isGroup": false, "isLive": false, "id": 42, "fieldTranslations": {"nameTranslation": {"hi": "\u092c\u0941\u0902\u0921\u0947\u0938\u0932\u0940\u0917\u093e", "ar": "\u0627\u0644\u062f\u0648\u0631\u064a \u0627\u0644\u0623\u0644\u0645\u0627\u0646\u064a", "bn": "\u09ac\u09c1\u09a8\u09cd\u09a6\u09c7\u09b8\u09b2\u09c0\u0997\u09be"}, "shortNameTranslation": {}}}, "season": {"name": "Bundesliga 24/25", "year": "24/25", "editor": false, "id": 63516}, "roundInfo": {"round": 9}, "customId": "CdbsGdb", "status": {"code": 100, "description": "Ended", "type": "finished"}, "winnerCode": 3, "homeTeam": {"name": "Bayer 04 Leverkusen", "slug": "bayer-04-leverkusen", "shortName": "Leverkusen", "gender": "M", "sport": {"name": "Football", "slug": "football", "id": 1}, "userCount": 1004655, "nameCode": "B04", "disabled": false, "national": false, "type": 0, "country": {"alpha2": "DE", "alpha3": "DEU", "name": "Germany", "slug": "germany"}, "id": 2681, "subTeams": [], "teamColors": {"primary": "#000000", "secondary": "#ff2222", "text": "#ff2222"}, "fieldTranslations": {"nameTranslation": {"ar": "\u0628\u0627\u064a\u0631 04 \u0644\u064a\u0641\u0631\u0643\u0648\u0632\u0646", "ru": "\u0411\u0430\u0439\u0435\u0440 \u041b\u0435\u0432\u0435\u0440\u043a\u0443\u0437\u0435\u043d"}, "shortNameTranslation": {"ar": "\u0644\u064a\u0641\u0631\u0643\u0648\u0632\u0646", "bn": "\u09b2\u09c7\u09ad\u09be\u09b0\u0995\u09c1\u09b8\u09c7\u09a8", "hi": "\u0932\u0947\u0935\u0930\u0915\u0941\u0938\u0947\u0928"}}}, "awayTeam": {"name": "VfB Stuttgart", "slug": "vfb-stuttgart", "shortName": "Stuttgart", "gender": "M", "sport": {"name": "Football", "slug": "football", "id": 1}, "userCount": 237669, "nameCode": "VFB", "disabled": false, "national": false, "type": 0, "country": {"alpha2": "DE", "alpha3": "DEU", "name": "Germany", "slug": "germany"}, "id": 2677, "subTeams": [], "teamColors": {"primary": "#ffffff", "secondary": "#ff0000", "text": "#ff0000"}, "fieldTranslations": {"nameTranslation": {"ar": "\u0634\u062a\u0648\u062a\u062c\u0627\u0631\u062a", "hi": "VFB \u0938\u094d\u091f\u0941\u091f\u0917\u093e\u0930\u094d\u091f", "ru": "\u0428\u0442\u0443\u0442\u0433\u0430\u0440\u0442"}, "shortNameTranslation": {"ar": "\u0634\u062a\u0648\u062a\u063a\u0627\u0631\u062a", "bn": "\u09b8\u09cd\u099f\u09c1\u099f\u0997\u09be\u09b0\u09cd\u099f", "hi": "\u0938\u094d\u091f\u0941\u091f\u0917\u093e\u0930\u094d\u091f"}}}, "homeScore": {"current": 0, "display": 0, "period1": 0, "period2": 0, "normaltime": 0}, "awayScore": {"current": 0, "display": 0, "period1": 0, "period2": 0, "normaltime": 0}, "time": {"injuryTime1": 1, "injuryTime2": 3, "currentPeriodStartTimestamp": 1730493207}, "changes": {"changes": ["status.code", "status.description", "status.type"], "changeTimestamp": 1730496143}, "hasGlobalHighlights": false, "hasXg": true, "hasEventPlayerStatistics": true, "hasEventPlayerHeatMap": true, "detailId": 1, "crowdsourcingDataDisplayEnabled": false, "id": 12499743, "slug": "bayer-04-leverkusen-vfb-stuttgart", "startTimestamp": 1730489400, "finalResultOnly": false, "feedLocked": true, "isEditor": false, "_stats": {"home_ballPossession": 52, "away_ballPossession": 48, "home_expectedGoals": 2.36, "away_expectedGoals": 0.28, "home_bigChanceCreated": 5, "away_bigChanceCreated": 0, "home_totalShotsOnGoal": 19, "away_totalShotsOnGoal": 4, "home_goalkeeperSaves": 1, "away_goalkeeperSaves": 5, "home_cornerKicks": 10, "away_cornerKicks": 2, "home_fouls": 13, "away_fouls": 14, "home_passes": 447, "away_passes": 433, "home_totalTackle": 10, "away_totalTackle": 14, "home_freeKicks": 14, "away_freeKicks": 13, "home_yellowCards": 3, "away_yellowCards": 4, "home_shotsOnGoal": 5, "away_shotsOnGoal": 1, "home_hitWoodwork": 2, "away_hitWoodwork": 0, "home_shotsOffGoal": 9, "away_shotsOffGoal": 2, "home_blockedScoringAttempt": 5, "away_blockedScoringAttempt": 1, "home_totalShotsInsideBox": 15, "away_totalShotsInsideBox": 3, "home_totalShotsOutsideBox": 4, "away_totalShotsOutsideBox": 1, "home_bigChanceMissed": 5, "away_bigChanceMissed": 0, "home_accurateThroughBall": 3, "away_accurateThroughBall": 0, "home_touchesInOppBox": 30, "away_touchesInOppBox": 12, "home_fouledFinalThird": 1, "away_fouledFinalThird": 1, "home_offsides": 9, "away_offsides": 0, "home_accuratePasses": 374, "away_accuratePasses": 349, "home_throwIns": 18, "away_throwIns": 9, "home_finalThirdEntries": 63, "away_finalThirdEntries": 45, "home_finalThirdPhaseStatistic": 110, "away_finalThirdPhaseStatistic": 70, "home_accurateLongBalls": 27, "away_accurateLongBalls": 30, "home_accurateCross": 9, "away_accurateCross": 0, "home_duelWonPercent": 56, "away_duelWonPercent": 44, "home_dispossessed": 5, "away_dispossessed": 8, "home_groundDuelsPercentage": 38, "away_groundDuelsPercentage": 33, "home_aerialDuelsPercentage": 17, "away_aerialDuelsPercentage": 10, "home_dribblesPercentage": 17, "away_dribblesPercentage": 6, "home_wonTacklePercent": 5, "away_wonTacklePercent": 8, "home_interceptionWon": 8, "away_interceptionWon": 11, "home_ballRecovery": 50, "away_ballRecovery": 41, "home_totalClearance": 13, "away_totalClearance": 31, "home_goalsPrevented": 0.107, "away_goalsPrevented": 0.7291, "home_goalKicks": 6, "away_goalKicks": 10}}