{"eventState": {}, "tournament": {"name": "Liga Portugal Betclic", "slug": "liga-portugal-betclic", "category": {"name": "Portugal", "slug": "portugal", "sport": {"name": "Football", "slug": "football", "id": 1}, "country": {"alpha2": "PT", "alpha3": "PRT", "name": "Portugal", "slug": "portugal"}, "id": 44, "flag": "portugal", "alpha2": "PT", "fieldTranslations": {"nameTranslation": {"ar": "\u0627\u0644\u0628\u0631\u062a\u063a\u0627\u0644", "ru": "\u041f\u043e\u0440\u0442\u0443\u0433\u0430\u043b\u0438\u044f"}, "shortNameTranslation": {}}}, "uniqueTournament": {"name": "Liga Portugal Betclic", "slug": "liga-portugal-betclic", "primaryColorHex": "#ffc501", "secondaryColorHex": "#e6a100", "category": {"name": "Portugal", "slug": "portugal", "sport": {"name": "Football", "slug": "football", "id": 1}, "country": {"alpha2": "PT", "alpha3": "PRT", "name": "Portugal", "slug": "portugal"}, "id": 44, "flag": "portugal", "alpha2": "PT", "fieldTranslations": {"nameTranslation": {"ar": "\u0627\u0644\u0628\u0631\u062a\u063a\u0627\u0644", "ru": "\u041f\u043e\u0440\u0442\u0443\u0433\u0430\u043b\u0438\u044f"}, "shortNameTranslation": {}}}, "userCount": 149773, "hasPerformanceGraphFeature": true, "country": {}, "id": 238, "hasEventPlayerStatistics": true, "displayInverseHomeAwayTeams": false, "fieldTranslations": {"nameTranslation": {"ar": "\u062f\u0648\u0631\u064a \u0628\u064a\u062a\u0643\u0644\u064a\u0643 \u0627\u0644\u0628\u0631\u062a\u063a\u0627\u0644\u064a", "bn": "\u09b2\u09bf\u0997\u09be \u09aa\u09b0\u09cd\u09a4\u09c1\u0997\u09be\u09b2 \u09ac\u09c7\u099f\u0995\u09cd\u09b2\u09bf\u0995", "hi": "\u0932\u0940\u0917\u093e \u092a\u0941\u0930\u094d\u0924\u0917\u093e\u0932 \u092c\u0947\u091f\u0915\u094d\u0932\u093f\u0915"}, "shortNameTranslation": {}}}, "priority": 518, "isGroup": false, "isLive": false, "id": 52, "fieldTranslations": {"nameTranslation": {"ar": "\u0627\u0644\u062f\u0648\u0631\u064a \u0627\u0644\u0628\u0631\u062a\u063a\u0627\u0644\u064a \u0628\u064a\u062a\u0643\u0644\u064a\u0643", "bn": "\u09b2\u09bf\u0997\u09be \u09aa\u09b0\u09cd\u09a4\u09c1\u0997\u09be\u09b2 \u09ac\u09c7\u099f\u0995\u09cd\u09b2\u09bf\u0995", "hi": "\u0932\u0940\u0917\u093e \u092a\u0941\u0930\u094d\u0924\u0917\u093e\u0932 \u092c\u0947\u091f\u0915\u094d\u0932\u093f\u0915"}, "shortNameTranslation": {}}}, "season": {"name": "Liga Portugal 24/25", "year": "24/25", "editor": false, "id": 63670}, "roundInfo": {"round": 9}, "customId": "gkbsLkb", "status": {"code": 100, "description": "Ended", "type": "finished"}, "winnerCode": 1, "homeTeam": {"name": "Benfica", "slug": "benfica", "shortName": "Benfica", "gender": "M", "sport": {"name": "Football", "slug": "football", "id": 1}, "userCount": 854191, "nameCode": "SLB", "disabled": false, "national": false, "type": 0, "country": {"alpha2": "PT", "alpha3": "PRT", "name": "Portugal", "slug": "portugal"}, "id": 3006, "subTeams": [], "teamColors": {"primary": "#cc0000", "secondary": "#ffffff", "text": "#ffffff"}, "fieldTranslations": {"nameTranslation": {"ar": "\u0628\u0646\u0641\u064a\u0643\u0627", "bn": "\u09ac\u09c7\u09a8\u09ab\u09bf\u0995\u09be", "hi": "\u092c\u0947\u0928\u092b\u093f\u0915\u093e", "ru": "\u0411\u0435\u043d\u0444\u0438\u043a\u0430"}, "shortNameTranslation": {}}}, "awayTeam": {"name": "Rio Ave", "slug": "rio-ave", "shortName": "Rio Ave", "gender": "M", "sport": {"name": "Football", "slug": "football", "id": 1}, "userCount": 33380, "nameCode": "RAV", "disabled": false, "national": false, "type": 0, "country": {"alpha2": "PT", "alpha3": "PRT", "name": "Portugal", "slug": "portugal"}, "id": 3036, "subTeams": [], "teamColors": {"primary": "#006633", "secondary": "#ffffff", "text": "#ffffff"}, "fieldTranslations": {"nameTranslation": {"ar": "\u0631\u064a\u0648 \u0627\u0641\u064a", "bn": "\u09b0\u09bf\u0993 \u098f\u09ad", "hi": "\u0930\u093f\u092f\u094b \u090f\u0935", "ru": "\u0420\u0438\u0443 \u0410\u0432\u0435"}, "shortNameTranslation": {}}}, "homeScore": {"current": 5, "display": 5, "period1": 3, "period2": 2, "normaltime": 5}, "awayScore": {"current": 0, "display": 0, "period1": 0, "period2": 0, "normaltime": 0}, "time": {"injuryTime1": 3, "injuryTime2": 2, "currentPeriodStartTimestamp": 1730056065}, "changes": {"changes": ["time.injuryTime2", "status.code", "status.description", "status.type"], "changeTimestamp": 1730058909}, "hasGlobalHighlights": false, "hasXg": true, "hasEventPlayerStatistics": true, "hasEventPlayerHeatMap": true, "detailId": 1, "crowdsourcingDataDisplayEnabled": false, "id": 12514051, "slug": "rio-ave-benfica", "startTimestamp": 1730052000, "finalResultOnly": false, "feedLocked": true, "isEditor": false, "_stats": {"home_ballPossession": 62, "away_ballPossession": 38, "home_expectedGoals": 2.38, "away_expectedGoals": 0.19, "home_bigChanceCreated": 4, "away_bigChanceCreated": 0, "home_totalShotsOnGoal": 29, "away_totalShotsOnGoal": 4, "home_goalkeeperSaves": 0, "away_goalkeeperSaves": 8, "home_cornerKicks": 8, "away_cornerKicks": 2, "home_fouls": 12, "away_fouls": 10, "home_passes": 527, "away_passes": 333, "home_totalTackle": 17, "away_totalTackle": 25, "home_freeKicks": 9, "away_freeKicks": 12, "home_yellowCards": 1, "away_yellowCards": 1, "home_shotsOnGoal": 14, "away_shotsOnGoal": 0, "home_hitWoodwork": 0, "away_hitWoodwork": 0, "home_shotsOffGoal": 8, "away_shotsOffGoal": 3, "home_blockedScoringAttempt": 7, "away_blockedScoringAttempt": 1, "home_totalShotsInsideBox": 19, "away_totalShotsInsideBox": 1, "home_totalShotsOutsideBox": 10, "away_totalShotsOutsideBox": 3, "home_bigChanceScored": 2, "away_bigChanceScored": 0, "home_bigChanceMissed": 2, "away_bigChanceMissed": 0, "home_accurateThroughBall": 2, "away_accurateThroughBall": 0, "home_touchesInOppBox": 65, "away_touchesInOppBox": 2, "home_fouledFinalThird": 2, "away_fouledFinalThird": 1, "home_offsides": 5, "away_offsides": 3, "home_accuratePasses": 459, "away_accuratePasses": 260, "home_throwIns": 25, "away_throwIns": 22, "home_finalThirdEntries": 55, "away_finalThirdEntries": 29, "home_finalThirdPhaseStatistic": 151, "away_finalThirdPhaseStatistic": 32, "home_accurateLongBalls": 20, "away_accurateLongBalls": 24, "home_accurateCross": 10, "away_accurateCross": 1, "home_duelWonPercent": 48, "away_duelWonPercent": 52, "home_dispossessed": 10, "away_dispossessed": 8, "home_groundDuelsPercentage": 35, "away_groundDuelsPercentage": 45, "home_aerialDuelsPercentage": 8, "away_aerialDuelsPercentage": 2, "home_dribblesPercentage": 9, "away_dribblesPercentage": 8, "home_wonTacklePercent": 13, "away_wonTacklePercent": 9, "home_interceptionWon": 12, "away_interceptionWon": 14, "home_ballRecovery": 55, "away_ballRecovery": 48, "home_totalClearance": 5, "away_totalClearance": 34, "home_errorsLeadToShot": 0, "away_errorsLeadToShot": 1, "home_goalsPrevented": 0, "away_goalsPrevented": -1.0313, "home_diveSaves": 0, "away_diveSaves": 1, "home_goalKicks": 4, "away_goalKicks": 9}}